{
    "main": {
        "name":"Cameron Redmond",
        "description":"I am a software engineer",
        "bio":"I grew up in ..",
        "email":"cam.redmond19@gmail.com",
        "phone":"416-705-1620",
        "github":"https://github.com/camRedmond",
        "linked-in":"https://www.linkedin.com/",
        "website":"camredmond.com"
    },
    "resume": {
        "skillmessage":"Here you can create a short write-up of your skills to show off to employers",
        "education":[
            {
                "school":"Wilfrid Laurier University",
                "degree":"Computer Science Major",
                "graduated":"Dec. 2021",
                "description":"Machine Learning  |  Quantum Computing  |  Foundations of Computing  |  Data Structures I/II  |  Data Mining  |  Applied Cryptography  |  Algorithm Design/Analysis  |  Computer Networks  |  Databases I/II  |  Internet Computing  |"
            }
        ],
        "work":[
            {
              "company":"Öviinbyrd Golf Course",
              "title":"Golf Operations Supervisor",
              "years":"Summer 2017 - 2020",
              "description":"Describe work, special projects, notable achievements, what technologies you have been working with, and anything else that would be useful for an employer to know."
            }
        ],
        "skills":[
            {
                "name":"Python",
                "png":"./img/python.png"
            },
            {
                "name":"Java",
                "png":"./img/java.png"
            },
            {
                "name":"C",
                "png":"./img/c-lang.png"
            },
            {
                "name":"Javascript",
                "png":"./img/Javascript.png"
            },
            {
                "name":"PHP",
                "png":"./img/php.png"
            },
            {
                "name":"React",
                "png":"./img/react.png"
            },
            {
                "name":"Git",
                "png":"./img/git.png"
            },
            {
                "name":"Flash",
                "png":"./img/python-flask.png"
            }       
        ]
    }
}